setup.py
savant/__init__.py
savant.egg-info/PKG-INFO
savant.egg-info/SOURCES.txt
savant.egg-info/dependency_links.txt
savant.egg-info/top_level.txt
savant.egg-info/zip-safe