Metadata-Version: 1.0
Name: savant
Version: 0.2
Summary: Scrape video links from Google Drive
Home-page: https://github.com/yowmamasita/savant
Author: Ben Sarmiento
Author-email: me@bensarmiento.com
License: MIT
Platform: UNKNOWN
